limecord/__init__.py
limecord/bot.py
Limecord-0.0.1.dist-info/LICENSE
Limecord-0.0.1.dist-info/METADATA
Limecord-0.0.1.dist-info/WHEEL
Limecord-0.0.1.dist-info/top_level.txt
Limecord-0.0.1.dist-info/RECORD
