Metadata-Version: 2.1
Name: Limecord
Version: 0.0.1
Summary: Discord.py rework for better functionality
Author-email: LimeGradient <limegradientyt@gmail.com>
Project-URL: Homepage, https://github.com/pypa/limecord
Project-URL: Issues, https://github.com/pypa/limecord/issues
Classifier: Programming Language :: Python :: 3
Classifier: License :: OSI Approved :: MIT License
Classifier: Operating System :: OS Independent
Requires-Python: >=3.8
License-File: LICENSE
